password_portal/server.py
password_portal-0.0.0.dist-info/METADATA
password_portal-0.0.0.dist-info/WHEEL
password_portal-0.0.0.dist-info/entry_points.txt
password_portal-0.0.0.dist-info/top_level.txt
password_portal-0.0.0.dist-info/RECORD
